pycalbi/pycalbi.py
pycalbi-0.0.10.dist-info/METADATA
pycalbi-0.0.10.dist-info/WHEEL
pycalbi-0.0.10.dist-info/top_level.txt
pycalbi-0.0.10.dist-info/RECORD
