Metadata-Version: 2.1
Name: pycalbi
Version: 0.0.10
Summary: This lib provides concurrent support to IntelMQ bots 
Home-page: https://github.com/csirtamericas/CALBI
Author: Federico Carrilao, Einar Lanfranco
License: MIT
Keywords: python, package, distribution
Classifier: License :: OSI Approved :: MIT License
Classifier: Natural Language :: English
Classifier: Operating System :: OS Independent
Classifier: Programming Language :: Python :: 3
Classifier: Topic :: Software Development :: Libraries :: Python Modules
Requires-Python: >=3.6
Requires-Dist: redis
